LICENSE
pulsechain/__init__.py
pulsechain/client.py
pulsechain/exceptions.py
pulsechain/models.py
pulsechain/req_handler.py
pulsechain/subclients/__init__.py
pulsechain/subclients/addresses.py
pulsechain/subclients/blocks.py
pulsechain/subclients/search.py
pulsechain/subclients/smart_contracts.py
pulsechain/subclients/stats.py
pulsechain/subclients/subpath_client.py
pulsechain/subclients/tokens.py
pulsechain/subclients/transactions.py
pulsechain/utils.py
pulsechain/validators.py
python_pulsechain-0.3.1.dist-info/LICENSE
python_pulsechain-0.3.1.dist-info/METADATA
python_pulsechain-0.3.1.dist-info/WHEEL
python_pulsechain-0.3.1.dist-info/RECORD
