Metadata-Version: 2.1
Name: python-pulsechain
Version: 0.3.1
Summary: Python implementation for PulseChain API
Home-page: https://github.com/crypto-ralph/python-pulsechain
License: GPL-3.0
Author: CryptoRalph
Author-email: doxter@protonmail.com
Requires-Python: >=3.10,<4.0
Classifier: License :: OSI Approved :: GNU General Public License v3 (GPLv3)
Classifier: Programming Language :: Python :: 3
Classifier: Programming Language :: Python :: 3.10
Classifier: Programming Language :: Python :: 3.11
Classifier: Programming Language :: Python :: 3.12
Requires-Dist: httpx (>=0.27.0,<0.28.0)
Requires-Dist: pydantic (>=2.8.2,<3.0.0)
Project-URL: Documentation, https://python-pulsechain.readthedocs.io/
Project-URL: Repository, https://github.com/crypto-ralph/python-pulsechain
